ultra_logger/__init__.py
ultra_logger/logger.py
ultra_logger-0.1.2.dist-info/METADATA
ultra_logger-0.1.2.dist-info/WHEEL
ultra_logger-0.1.2.dist-info/top_level.txt
ultra_logger-0.1.2.dist-info/RECORD
